README.rst
setup.py
nemo/__init__.py
nemo/datasets/__init__.py
nemo/datasets/pascal3d.py
nemo/models/__init__.py
nemo/models/base_model.py
nemo/models/feature_banks.py
nemo/models/keypoint_representation_net.py
nemo/models/mesh_interpolate_module.py
nemo/models/mesh_memory_map.py
nemo/models/nemo.py
nemo/models/resnet.py
nemo/models/solve_pose.py
nemo/models/unet.py
nemo/models/upsampling_layer.py
nemo/utils/__init__.py
nemo/utils/calculate_occ.py
nemo/utils/calculate_point_direction.py
nemo/utils/configuration.py
nemo/utils/data_preparation.py
nemo/utils/distributed_utils.py
nemo/utils/dnnlib.py
nemo/utils/evaluate.py
nemo/utils/features.py
nemo/utils/flow_warp.py
nemo/utils/general.py
nemo/utils/mesh.py
nemo/utils/pascal3d_utils.py
nemo/utils/pose.py
nemo/utils/process_camera_parameters.py
neural_mesh_model.egg-info/PKG-INFO
neural_mesh_model.egg-info/SOURCES.txt
neural_mesh_model.egg-info/dependency_links.txt
neural_mesh_model.egg-info/not-zip-safe
neural_mesh_model.egg-info/top_level.txt