Metadata-Version: 2.1
Name: neural-mesh-model
Version: 1.0.0
Summary: Neural mesh models for 3D reasoning.
Home-page: https://github.com/wufeim/NeMo
Author: Wufei Ma, Artur Jesslen
Author-email: wufeim@gmail.com
License: MIT license
Classifier: License :: OSI Approved :: MIT License
Classifier: Natural Language :: English
Classifier: Programming Language :: Python :: 3
Classifier: Programming Language :: Python :: 3.6
Classifier: Programming Language :: Python :: 3.7
Classifier: Programming Language :: Python :: 3.8
Classifier: Programming Language :: Python :: 3.9
Classifier: Programming Language :: Python :: 3.10
Requires-Python: >=3.6
